gremlin/__init__.py
gremlin/aws/__init__.py
gremlin/aws/dynamo.py
gremlin/aws/kms.py
gremlin/aws/s3.py
gremlin/db/lmdb.py
gremlin/discord/__init__.py
gremlin/discord/audio.py
gremlin/discord/auth.py
gremlin/discord/test_ytdl.py
gremlin/discord/timestamps.py
gremlin/discord/ytdl.py
gremlin/web/__init__.py
gremlin/web/requests.py
cutegremlin-1.1.10.dist-info/METADATA
cutegremlin-1.1.10.dist-info/WHEEL
cutegremlin-1.1.10.dist-info/top_level.txt
cutegremlin-1.1.10.dist-info/RECORD
