Metadata-Version: 2.1
Name: cutegremlin
Version: 1.1.10
Summary: A bunch of painfully dull helpers for AWS, Discord, and others resources.
Home-page: https://github.com/JesseZhong/cutegremlin
Author: Jesse
Author-email: jessetakuto@gmail.com
License: MIT
Platform: UNKNOWN
Requires-Dist: boto3
Requires-Dist: requests
Requires-Dist: discord.py
Requires-Dist: python-dotenv
Requires-Dist: youtube-dl
Requires-Dist: yt-dlp
Requires-Dist: lmdb
